async_jaeger/__init__.py
async_jaeger/codecs.py
async_jaeger/constants.py
async_jaeger/helpers.py
async_jaeger/jaeger.thrift
async_jaeger/py.typed
async_jaeger/rate_limiter.py
async_jaeger/reporter.py
async_jaeger/sampler.py
async_jaeger/span.py
async_jaeger/span_context.py
async_jaeger/thrift.py
async_jaeger/throttler.py
async_jaeger/tracer.py
async_jaeger/utils.py
async_jaeger/version.py
async_jaeger/metrics/__init__.py
async_jaeger/metrics/metrics.py
async_jaeger-0.0.13.dist-info/LICENSE
async_jaeger-0.0.13.dist-info/METADATA
async_jaeger-0.0.13.dist-info/WHEEL
async_jaeger-0.0.13.dist-info/top_level.txt
async_jaeger-0.0.13.dist-info/RECORD
