Metadata-Version: 2.1
Name: async-jaeger
Version: 0.0.13
Summary: Jaeger Python OpenTracing Tracer implementation for AsyncIO
Home-page: https://github.com/alvassin/async-jaeger
Author: Alexander Vasin
Author-email: hi@alvass.in
License: Apache License 2.0
Keywords: jaeger,tracing,opentracing
Platform: UNKNOWN
Classifier: Development Status :: 5 - Production/Stable
Classifier: Intended Audience :: Developers
Classifier: License :: OSI Approved :: Apache Software License
Classifier: Natural Language :: English
Classifier: Programming Language :: Python :: 3.7
Classifier: Programming Language :: Python :: 3.8
Classifier: Programming Language :: Python :: 3.9
Requires-Python: >=3.7
License-File: LICENSE
Requires-Dist: aiohttp
Requires-Dist: opentracing (<3.0,>=2.1)
Requires-Dist: thriftpy2
Provides-Extra: tests
Requires-Dist: aiomisc ; extra == 'tests'
Requires-Dist: mock ; extra == 'tests'
Requires-Dist: pytest ; extra == 'tests'
Requires-Dist: pytest-cov ; extra == 'tests'
Requires-Dist: coverage ; extra == 'tests'
Requires-Dist: pytest-timeout ; extra == 'tests'
Requires-Dist: pytest-benchmark[histogram] ; extra == 'tests'
Requires-Dist: pytest-localserver ; extra == 'tests'
Requires-Dist: flake8 ; extra == 'tests'
Requires-Dist: flake8-quotes ; extra == 'tests'
Requires-Dist: flake8-typing-imports ; extra == 'tests'
Requires-Dist: codecov ; extra == 'tests'
Requires-Dist: opentracing-instrumentation (<4,>=3) ; extra == 'tests'
Requires-Dist: types-setuptools ; extra == 'tests'
Requires-Dist: mypy ; extra == 'tests'
